{
  "action": {
    "danger": {
      "bg": {
        "$type": "color",
        "$value": "{colors.lost.4}"
      },
      "icon": {
        "$type": "color",
        "$value": "{colors.neutral.0}"
      },
      "text": {
        "$type": "color",
        "$value": "{colors.neutral.0}"
      }
    },
    "primary": {
      "bg": {
        "$type": "color",
        "$value": "#1988b8"
      },
      "icon": {
        "$type": "color",
        "$value": "#f1f2f3"
      },
      "text": {
        "$type": "color",
        "$value": "#f1f2f3"
      }
    },
    "secondary": {
      "bg": {
        "$type": "color",
        "$value": "#98d6f1"
      },
      "icon": {
        "$type": "color",
        "$value": "#0e4c67"
      },
      "text": {
        "$type": "color",
        "$value": "#0e4c67"
      }
    },
    "tertiary": {
      "bg": {
        "$type": "color",
        "$value": "#ffffff"
      },
      "icon": {
        "$type": "color",
        "$value": "#1988b8"
      },
      "text": {
        "$type": "color",
        "$value": "#1988b8"
      }
    }
  },
  "bg": {
    "primary": {
      "$type": "color",
      "$value": "#ffffff"
    },
    "prueba prueba": {
      "$type": "color",
      "$value": "{colors.acco.2}"
    },
    "secondary": {
      "$type": "color",
      "$value": "#f1f2f3"
    }
  },
  "border": {
    "primary": {
      "$type": "color",
      "$value": "#ffffff"
    },
    "secondary": {
      "$type": "color",
      "$value": "#ffffff"
    }
  },
  "feedback": {
    "error": {
      "$type": "color",
      "$value": "#c01111"
    },
    "info": {
      "$type": "color",
      "$value": "#1174c0"
    },
    "success": {
      "$type": "color",
      "$value": "#11c074"
    },
    "warning": {
      "$type": "color",
      "$value": "#c09111"
    }
  },
  "icon": {
    "disabled": {
      "$type": "color",
      "$value": "{colors.calm.1}"
    },
    "primary": {
      "$type": "color",
      "$value": "#ffffff"
    },
    "secondary": {
      "$type": "color",
      "$value": "#ffffff"
    },
    "tertiary": {
      "$type": "color",
      "$value": "#ffffff"
    }
  },
  "overlay": {
    "hover 2": {
      "$type": "color",
      "$value": "#00000014"
    },
    "pressed 2": {
      "$type": "color",
      "$value": "#00000029"
    }
  },
  "surface": {
    "primary": {
      "$type": "color",
      "$value": "#bfc3ca"
    },
    "secondary": {
      "$type": "color",
      "$value": "#f1f2f3"
    }
  },
  "text": {
    "disabled": {
      "$type": "color",
      "$value": "#bfc3ca"
    },
    "primary": {
      "$type": "color",
      "$value": "#0c0c0e"
    },
    "secondary": {
      "$type": "color",
      "$value": "#5f6572"
    }
  }
}